<?xml version="1.0"?>
<rsp status_code="0" status_message="Success">
  <daily_counts>
    <count date="20180727T00:00:00">0</count>
    <count date="20180728T00:00:00">0</count>
    <count date="20180729T00:00:00">0</count>
    <count date="20180730T00:00:00">0</count>
    <count date="20180731T00:00:00">0</count>
    <count date="20180801T00:00:00">0</count>
    <count date="20180802T00:00:00">0</count>
    <count date="20180803T00:00:00">0</count>
    <count date="20180804T00:00:00">0</count>
    <count date="20180805T00:00:00">0</count>
    <count date="20180806T00:00:00">0</count>
    <count date="20180807T00:00:00">0</count>
    <count date="20180808T00:00:00">0</count>
    <count date="20180809T00:00:00">0</count>
    <count date="20180810T00:00:00">0</count>
    <count date="20180811T00:00:00">0</count>
    <count date="20180812T00:00:00">0</count>
    <count date="20180813T00:00:00">0</count>
    <count date="20180814T00:00:00">0</count>
    <count date="20180815T00:00:00">0</count>
    <count date="20180816T00:00:00">0</count>
    <count date="20180817T00:00:00">0</count>
    <count date="20180818T00:00:00">0</count>
    <count date="20180819T00:00:00">0</count>
    <count date="20180820T00:00:00">0</count>
    <count date="20180821T00:00:00">0</count>
    <count date="20180822T00:00:00">0</count>
    <count date="20180823T00:00:00">0</count>
    <count date="20180824T00:00:00">0</count>
    <count date="20180825T00:00:00">0</count>
    <count date="20180826T00:00:00">0</count>
    <count date="20180827T00:00:00">0</count>
    <count date="20180828T00:00:00">0</count>
    <count date="20180829T00:00:00">0</count>
    <count date="20180830T00:00:00">0</count>
    <count date="20180831T00:00:00">0</count>
    <count date="20180901T00:00:00">0</count>
    <count date="20180902T00:00:00">0</count>
    <count date="20180903T00:00:00">0</count>
    <count date="20180904T00:00:00">0</count>
    <count date="20180905T00:00:00">0</count>
    <count date="20180906T00:00:00">0</count>
    <count date="20180907T00:00:00">0</count>
    <count date="20180908T00:00:00">0</count>
    <count date="20180909T00:00:00">0</count>
    <count date="20180910T00:00:00">0</count>
    <count date="20180911T00:00:00">1</count>
    <count date="20180912T00:00:00">0</count>
    <count date="20180913T00:00:00">0</count>
    <count date="20180914T00:00:00">0</count>
    <count date="20180915T00:00:00">0</count>
    <count date="20180916T00:00:00">0</count>
    <count date="20180917T00:00:00">0</count>
    <count date="20180918T00:00:00">0</count>
    <count date="20180919T00:00:00">0</count>
    <count date="20180920T00:00:00">0</count>
    <count date="20180921T00:00:00">0</count>
    <count date="20180922T00:00:00">0</count>
    <count date="20180923T00:00:00">0</count>
    <count date="20180924T00:00:00">0</count>
    <count date="20180925T00:00:00">0</count>
    <count date="20180926T00:00:00">0</count>
    <count date="20180927T00:00:00">0</count>
    <count date="20180928T00:00:00">0</count>
    <count date="20180929T00:00:00">0</count>
    <count date="20180930T00:00:00">0</count>
    <count date="20181001T00:00:00">0</count>
    <count date="20181002T00:00:00">0</count>
    <count date="20181003T00:00:00">0</count>
    <count date="20181004T00:00:00">0</count>
    <count date="20181005T00:00:00">0</count>
    <count date="20181006T00:00:00">0</count>
    <count date="20181007T00:00:00">0</count>
    <count date="20181008T00:00:00">0</count>
    <count date="20181009T00:00:00">0</count>
    <count date="20181010T00:00:00">0</count>
    <count date="20181011T00:00:00">0</count>
    <count date="20181012T00:00:00">0</count>
    <count date="20181013T00:00:00">0</count>
    <count date="20181014T00:00:00">0</count>
    <count date="20181015T00:00:00">0</count>
    <count date="20181016T00:00:00">0</count>
    <count date="20181017T00:00:00">0</count>
    <count date="20181018T00:00:00">0</count>
    <count date="20181019T00:00:00">0</count>
    <count date="20181020T00:00:00">0</count>
    <count date="20181021T00:00:00">0</count>
    <count date="20181022T00:00:00">2</count>
    <count date="20181023T00:00:00">0</count>
    <count date="20181024T00:00:00">0</count>
    <count date="20181025T00:00:00">0</count>
    <count date="20181026T00:00:00">0</count>
    <count date="20181027T00:00:00">0</count>
    <count date="20181028T00:00:00">0</count>
    <count date="20181029T00:00:00">0</count>
    <count date="20181030T00:00:00">0</count>
    <count date="20181031T00:00:00">0</count>
    <count date="20181101T00:00:00">0</count>
    <count date="20181102T00:00:00">0</count>
    <count date="20181103T00:00:00">0</count>
    <count date="20181104T00:00:00">0</count>
    <count date="20181105T00:00:00">0</count>
    <count date="20181106T00:00:00">0</count>
    <count date="20181107T00:00:00">0</count>
    <count date="20181108T00:00:00">0</count>
    <count date="20181109T00:00:00">0</count>
    <count date="20181110T00:00:00">0</count>
    <count date="20181111T00:00:00">0</count>
    <count date="20181112T00:00:00">0</count>
    <count date="20181113T00:00:00">0</count>
    <count date="20181114T00:00:00">0</count>
    <count date="20181115T00:00:00">0</count>
    <count date="20181116T00:00:00">0</count>
    <count date="20181117T00:00:00">0</count>
    <count date="20181118T00:00:00">0</count>
    <count date="20181119T00:00:00">0</count>
    <count date="20181120T00:00:00">0</count>
    <count date="20181121T00:00:00">0</count>
    <count date="20181122T00:00:00">0</count>
    <count date="20181123T00:00:00">0</count>
  </daily_counts>
</rsp>
